mkdocs_autolinks_plugin/__init__.py
mkdocs_autolinks_plugin/plugin.py
mkdocs_autolinks_plugin-0.7.1.dist-info/LICENSE
mkdocs_autolinks_plugin-0.7.1.dist-info/METADATA
mkdocs_autolinks_plugin-0.7.1.dist-info/WHEEL
mkdocs_autolinks_plugin-0.7.1.dist-info/entry_points.txt
mkdocs_autolinks_plugin-0.7.1.dist-info/top_level.txt
mkdocs_autolinks_plugin-0.7.1.dist-info/RECORD
