Metadata-Version: 2.1
Name: mkdocs-autolinks-plugin
Version: 0.7.1
Summary: An MkDocs plugin
Home-page: https://github.com/midnightprioriem/mkdocs-autolinks-plugin
Download-URL: https://github.com/midnightprioriem/mkdocs-autolinks-plugin/archive/v_071.tar.gz
Author: Zach Hannum
Author-email: zacharyhannum@gmail.com
License: MIT
Keywords: mkdocs
Classifier: Development Status :: 4 - Beta
Classifier: Intended Audience :: Developers
Classifier: Intended Audience :: Information Technology
Classifier: License :: OSI Approved :: MIT License
Classifier: Programming Language :: Python
Classifier: Programming Language :: Python :: 3 :: Only
Classifier: Programming Language :: Python :: 3.4
Classifier: Programming Language :: Python :: 3.5
Classifier: Programming Language :: Python :: 3.6
Classifier: Programming Language :: Python :: 3.7
Requires-Python: >=3.4
License-File: LICENSE
Requires-Dist: mkdocs (>=1.2.3)
